ckr_lang/__init__.py
ckr_lang/__main__.py
ckr_lang/cli.py
ckr_lang/core.py
ckr_lang-0.1.7.dist-info/licenses/LICENSE
ckr_lang-0.1.7.dist-info/METADATA
ckr_lang-0.1.7.dist-info/WHEEL
ckr_lang-0.1.7.dist-info/entry_points.txt
ckr_lang-0.1.7.dist-info/top_level.txt
ckr_lang-0.1.7.dist-info/RECORD
