Metadata-Version: 2.4
Name: ckr_lang
Version: 0.1.7
Summary: A Fan-made Python interpreter for the ChoiKangRok Esolang
Author: hannim
Project-URL: Homepage, https://github.com/BK-Dan/ckr-lang
Keywords: esolang,choikangrok,interpreter,korean,fan-made,parody
Classifier: Programming Language :: Python :: 3
Classifier: License :: OSI Approved :: MIT License
Classifier: Operating System :: OS Independent
Classifier: Topic :: Software Development :: Interpreters
Requires-Python: >=3.8
License-File: LICENSE
Dynamic: license-file
